{
  "task_type": "error_handling",
  "task_name": "定時任務失敗處理",
  "timestamp": "2026-03-04T06:05:00Z",
  "scenario": {
    "description": "定時執行的 cron 任務失敗，收到 SIGTERM 信號",
    "session_id": "nova-fjo",
    "error_code": "SIGTERM",
    "execution_time": "06:01:48"
  },
  "expected_actions": [
    {
      "step": 1,
      "action": "記錄錯誤",
      "details": "建立 task-failure-YYYYMMDD-HHMM.md 錯誤日誌",
      "priority": "high"
    },
    {
      "step": 2,
      "action": "分析原因",
      "details": "檢查是否為系統性問題（超時/記憶體不足）",
      "priority": "high"
    },
    {
      "step": 3,
      "action": "安全監控",
      "details": "確認無安全威脅，更新 security.md",
      "priority": "medium"
    },
    {
      "step": 4,
      "action": "決定是否警報",
      "details": "單一偶發錯誤不需警報，系統性問題才觸發",
      "priority": "high"
    }
  ],
  "decision_criteria": {
    "alert_threshold": "3次以上同類錯誤 或 記憶體>95% 或 Context>90%",
    "non_urgent_signals": ["SIGTERM", "exit 1 (偶發)"],
    "urgent_signals": ["OOM", "多次重複失敗", "安全威脅"]
  },
  "result": {
    "status": "success",
    "actions_taken": ["記錄錯誤到 errors/", "更新 security.md", "判定為非緊急"],
    "alert_sent": false
  },
  "training_notes": "此案例展示如何區分緊急與非緊急錯誤，避免過度警報"
}
