{
  "task_type": "cron_reminder_handling",
  "timestamp": "2026-03-05T06:37:00+08:00",
  "input": {
    "reminder_content": "📚 訓練數據收集：1.記錄簡單重複工作 2.生成訓練範例 3.建立訓練數據集 4.儲存到 training-data/\nExec failed (cool-blo, signal SIGTERM)\n📊 Token實時監控：1.檢查當前Token使用 2.如超閾值則警報 3.記錄到 memory/token-analysis.md",
    "context": {
      "time": "2026-03-05 06:36 AM",
      "timezone": "Asia/Macau"
    }
  },
  "actions_taken": [
    {
      "step": 1,
      "action": "session_status",
      "reason": "Check current token usage for monitoring"
    },
    {
      "step": 2,
      "action": "ls training-data/",
      "reason": "Check existing training data"
    },
    {
      "step": 3,
      "action": "write training example",
      "reason": "Record this reminder handling as training data"
    },
    {
      "step": 4,
      "action": "update token-analysis.md",
      "reason": "Log token usage for trend analysis"
    }
  ],
  "output": {
    "token_usage": {
      "input_tokens": 19000,
      "output_tokens": 850,
      "context_percent": 16,
      "cost_usd": 0.33,
      "cache_hit_rate": "90%",
      "status": "NORMAL"
    },
    "training_data_count": 108,
    "alert_triggered": false
  },
  "pattern": "Cron reminder handling follows pattern: 1) Check system status (session_status) 2) Check relevant data directories 3) Execute required actions 4) Log results",
  "success": true
}
