{
  "Name": "Content Topics",
  "Properties": {
    "Topic": {
      "title": {}
    },
    "Status": {
      "select": {
        "options": [
          {"name": "Pending", "color": "yellow"},
          {"name": "In Progress", "color": "blue"},
          {"name": "Ready for Review", "color": "purple"},
          {"name": "Approved", "color": "green"},
          {"name": "Published", "color": "gray"},
          {"name": "Rejected", "color": "red"}
        ]
      }
    },
    "Platform": {
      "multi_select": {
        "options": [
          {"name": "Twitter/X", "color": "blue"},
          {"name": "Instagram", "color": "pink"},
          {"name": "TikTok", "color": "cyan"},
          {"name": "YouTube", "color": "red"},
          {"name": "LinkedIn", "color": "blue"}
        ]
      }
    },
    "Created": {
      "date": {}
    },
    "Published Date": {
      "date": {}
    },
    "Thread Content": {
      "rich_text": {}
    },
    "Source Links": {
      "url": {}
    },
    "Notes": {
      "rich_text": {}
    }
  }
}
